aromatools/__init__.py
aromatools/aroenergetic/__init__.py
aromatools/arogeometric/__init__.py
aromatools/arogeometric/__main__.py
aromatools/arogeometric/arogeometric.py
aromatools/arogeometric/reporter.py
aromatools/aromagnetic/__init__.py
aromatools-0.1.86.dist-info/licenses/LICENSE
aromatools-0.1.86.dist-info/METADATA
aromatools-0.1.86.dist-info/WHEEL
aromatools-0.1.86.dist-info/top_level.txt
aromatools-0.1.86.dist-info/RECORD
