Metadata-Version: 2.4
Name: aromatools
Version: 0.1.86
Summary: Herramientas para el análisis de aromaticidad (HOMA, HOMAc, HOMER)
Author: Fernando Martínez Villarino
Author-email: fernandomv5897@gmail.com
License: MIT
Classifier: Programming Language :: Python :: 3
Classifier: License :: OSI Approved :: MIT License
Classifier: Operating System :: OS Independent
Requires-Python: >=3.10
License-File: LICENSE
Requires-Dist: numpy
Requires-Dist: networkx
Requires-Dist: matplotlib
Requires-Dist: art
Requires-Dist: ase
Requires-Dist: pandas
Requires-Dist: plotly
Dynamic: author
Dynamic: author-email
Dynamic: classifier
Dynamic: license
Dynamic: license-file
Dynamic: requires-dist
Dynamic: requires-python
Dynamic: summary
